hotaru/__init__.py
hotaru/__main__.py
hotaru/config.yaml
hotaru/config/__init__.py
hotaru/config/default.yaml
hotaru/config/hotaru.yaml
hotaru/config/clean/bgtocell.yaml
hotaru/config/clean/ratio3x.yaml
hotaru/config/clean/ratio3y.yaml
hotaru/config/clean/ratio3z4.yaml
hotaru/config/clean/simple.yaml
hotaru/config/cmd/default.yaml
hotaru/config/data/default.yaml
hotaru/config/data/tifmask.yaml
hotaru/config/dynamics/default.yaml
hotaru/config/env/default.yaml
hotaru/config/gui/default.yaml
hotaru/config/hydra/local.yaml
hotaru/config/hydra/job_logging/hotaru.yaml
hotaru/config/hydra/output/hotaru.yaml
hotaru/config/init/default.yaml
hotaru/config/outputs/default.yaml
hotaru/config/penalty/a0u0.yaml
hotaru/config/penalty/a0u1.yaml
hotaru/config/penalty/a0u10.yaml
hotaru/config/penalty/a0u100.yaml
hotaru/config/penalty/a0u5.yaml
hotaru/config/penalty/a100u0.yaml
hotaru/config/penalty/a100u1.yaml
hotaru/config/penalty/a100u10.yaml
hotaru/config/penalty/a100u100.yaml
hotaru/config/penalty/a100u5.yaml
hotaru/config/penalty/a10u0.yaml
hotaru/config/penalty/a10u1.yaml
hotaru/config/penalty/a10u10.yaml
hotaru/config/penalty/a10u100.yaml
hotaru/config/penalty/a10u5.yaml
hotaru/config/penalty/a1u0.yaml
hotaru/config/penalty/a1u1.yaml
hotaru/config/penalty/a1u10.yaml
hotaru/config/penalty/a1u100.yaml
hotaru/config/penalty/a1u5.yaml
hotaru/config/penalty/annealing_a100u10.yaml
hotaru/config/penalty/annealing_a10u1.yaml
hotaru/config/penalty/annealing_a10u10.yaml
hotaru/config/penalty/annealing_a10u5.yaml
hotaru/config/penalty/annealing_a1u1.yaml
hotaru/config/penalty/annealing_a1u5.yaml
hotaru/config/penalty/zero.yaml
hotaru/config/radius/default.yaml
hotaru/cui/__init__.py
hotaru/cui/common.py
hotaru/cui/data.py
hotaru/cui/init.py
hotaru/cui/normalize.py
hotaru/cui/plotter.py
hotaru/cui/run.py
hotaru/cui/spatial.py
hotaru/cui/temporal.py
hotaru/cui/test.py
hotaru/filter/__init__.py
hotaru/filter/gaussian.py
hotaru/filter/laplace.py
hotaru/filter/map.py
hotaru-5.2.5.dist-info/METADATA
hotaru-5.2.5.dist-info/WHEEL
hotaru-5.2.5.dist-info/entry_points.txt
hotaru-5.2.5.dist-info/licenses/LICENSE
hotaru-5.2.5.dist-info/RECORD
