Metadata-Version: 2.4
Name: hotaru
Version: 5.2.5
Summary: High performance Optimizer to extract spike Timing And cell location from calcium imaging data via lineaR impUlse
Author-email: TAKEKAWA Takashi <takekawa@tk2lab.org>
License-Expression: GPL-3.0-only
License-File: LICENSE
Keywords: Calcium Imaging,Cell Extraction,Spike Detection
Requires-Python: >=3.11
Requires-Dist: av>=10.0
Requires-Dist: hydra-core>=1.3
Requires-Dist: jax<0.7,>=0.4.34; sys_platform == 'darwin'
Requires-Dist: jax[cuda12]<0.7,>=0.4.34; sys_platform == 'linux'
Requires-Dist: kaleido>=0.2.1
Requires-Dist: matplotlib>=3.7.2
Requires-Dist: pandas>=2.0.3
Requires-Dist: plotly>=5.0.0
Requires-Dist: psutil>=7.1.0
Requires-Dist: tensorflow>=2.13.0
Requires-Dist: tifffile>=2022.8
Requires-Dist: tqdm>=4.64
Requires-Dist: versioningit
